README.md
setup.py
raffiot/__init__.py
raffiot/_internal.py
raffiot/_runtime.py
raffiot/io.py
raffiot/py.typed
raffiot/resource.py
raffiot/result.py
raffiot/utils.py
raffiot/val.py
raffiot/var.py
raffiot.egg-info/PKG-INFO
raffiot.egg-info/SOURCES.txt
raffiot.egg-info/dependency_links.txt
raffiot.egg-info/not-zip-safe
raffiot.egg-info/requires.txt
raffiot.egg-info/top_level.txt
raffiot/untyped/__init__.py
raffiot/untyped/_internal.py
raffiot/untyped/_runtime.py
raffiot/untyped/io.py
raffiot/untyped/resource.py
raffiot/untyped/result.py
raffiot/untyped/utils.py
raffiot/untyped/val.py
raffiot/untyped/var.py