Metadata-Version: 2.1
Name: raffiot
Version: 0.6.0
Summary: Robust And Fast Functional IO Toolkit
Home-page: https://github.com/chrilves/raffiot.py
Author: chrilves
Author-email: calves@crans.org
License: Apache 2.0
Download-URL: https://github.com/chrilves/raffiot.py/archive/0.6.0.tar.gz
Keywords: IO,MONAD,FUNCTIONAL PROGRAMMING,RESULT,RESOURCE MANAGEMENT,RAILWAY
Platform: UNKNOWN
Classifier: Development Status :: 3 - Alpha
Classifier: Intended Audience :: Developers
Classifier: Topic :: Software Development :: Build Tools
Classifier: License :: OSI Approved :: Apache Software License
Classifier: Programming Language :: Python :: 3.7
Classifier: Programming Language :: Python :: 3.8
Classifier: Programming Language :: Python :: 3.9
Classifier: Operating System :: OS Independent
Requires-Python: >=3.7
